baserow/__init__.py
baserow/client.py
baserow/color.py
baserow/error.py
baserow/field.py
baserow/field_config.py
baserow/file.py
baserow/filter.py
baserow/table.py
baserowdantic-0.1.1.dist-info/LICENSE
baserowdantic-0.1.1.dist-info/WHEEL
baserowdantic-0.1.1.dist-info/METADATA
baserowdantic-0.1.1.dist-info/RECORD
