Metadata-Version: 2.1
Name: baserowdantic
Version: 0.1.1
Summary: Pydantic-based Baserow CRUD Client featuring ORM-like capabilities
Keywords: baserow,pydantic,no-code,orm,database
Author-email: 72nd <msg@frg72.com>
Requires-Python: >=3.9
Classifier: License :: OSI Approved :: MIT License
Classifier: Programming Language :: Python :: 3.9
Classifier: Operating System :: OS Independent
Requires-Dist: aiohttp
Requires-Dist: pydantic
Requires-Dist: typing_extensions
Requires-Dist: pdoc ; extra == "doc"
Project-URL: Documentation, https://72nd.github.io/baserowdantic/
Project-URL: Homepage, https://github.com/72nd/baserowdantic
Project-URL: Issues, https://github.com/72nd/baserowdantic/issues
Provides-Extra: doc
